AUTHORS
LICENSE
MANIFEST.in
README.rst
setup.py
django_gmaps.egg-info/PKG-INFO
django_gmaps.egg-info/SOURCES.txt
django_gmaps.egg-info/dependency_links.txt
django_gmaps.egg-info/top_level.txt
gmaps/__init__.py
gmaps/models.py
gmaps/tests.py
gmaps/templates/gmaps/templatetags/gmaps/gmap_js.html
gmaps/templates/gmaps/templatetags/gmaps/kwargs.js
gmaps/templates/gmaps/templatetags/gmaps/load_handler.js
gmaps/templates/gmaps/templatetags/gmaps/map.js
gmaps/templates/gmaps/templatetags/gmaps/marker.js
gmaps/templates/gmaps/templatetags/gmaps/polygon.js
gmaps/templates/gmaps/templatetags/gmaps/polyline.js
gmaps/templatetags/__init__.py
gmaps/templatetags/gmaps.py
tests/__init__.py