Metadata-Version: 1.0
Name: django-gmaps
Version: 0.0.3
Summary: Template tags for creating Google Maps from GeoDjango fields.
Home-page: https://github.com/fcurella/django-google-maps
Author: Flavio Curella
Author-email: flavio.curella@gmail.com
License: MIT
Platform: UNKNOWN
Classifier: Development Status :: 3 - Alpha
Classifier: Environment :: Console
Classifier: Intended Audience :: Developers
Classifier: Intended Audience :: Information Technology
Classifier: License :: OSI Approved :: MIT License
Classifier: Operating System :: OS Independent
Classifier: Programming Language :: Python
Classifier: Framework :: Django
